tf_datachain/ObjectDetection.py
tf_datachain/__init__.py
tf_datachain/utils.py
tf_datachain-0.1.0.dist-info/LICENSE
tf_datachain-0.1.0.dist-info/METADATA
tf_datachain-0.1.0.dist-info/WHEEL
tf_datachain-0.1.0.dist-info/top_level.txt
tf_datachain-0.1.0.dist-info/RECORD
