Metadata-Version: 2.1
Name: tf-datachain
Version: 0.1.0
Summary: A local dataset loader based on tf.data input pipeline
Author: Yiming Liu
Author-email: YimingDesigner@gmail.com
License-File: LICENSE
Requires-Dist: numpy
Requires-Dist: matplotlib
Requires-Dist: pandas
Requires-Dist: tensorflow
Requires-Dist: keras-cv
Requires-Dist: keras-core
Requires-Dist: opencv-python
